teg_get_best_n.py
teg_get_best_n-0.0.7.dist-info/LICENSE
teg_get_best_n-0.0.7.dist-info/METADATA
teg_get_best_n-0.0.7.dist-info/WHEEL
teg_get_best_n-0.0.7.dist-info/top_level.txt
teg_get_best_n-0.0.7.dist-info/RECORD
