Metadata-Version: 2.1
Name: teg-get-best-n
Version: 0.0.7
Summary: Estimate the optimal number of components in PCA-based dimension reduction.
Author-email: "Thomas E. Gladwin" <thomasgladwin@hotmail.com>
Project-URL: Homepage, https://tegladwin.com
Project-URL: Bug Tracker, https://github.com/thomasgladwin/teg_get_best_n
Classifier: Programming Language :: Python :: 3
Classifier: License :: OSI Approved :: MIT License
Classifier: Operating System :: OS Independent
Requires-Python: >=3.6
License-File: LICENSE
Requires-Dist: numpy
